{
  "resourceType" : "Practitioner",
  "id" : "9583c018-8e84-4729-9ac0-8c887b4e6c5e",
  "meta" : {
    "profile" : ["http://medcomfhir.dk/ig/core/StructureDefinition/medcom-core-practitioner|3.0.1"]
  },
  "text" : {
    "status" : "generated",
    "div" : "<div xmlns=\"http://www.w3.org/1999/xhtml\"><p class=\"res-header-id\"><b>Generated Narrative: Practitioner 9583c018-8e84-4729-9ac0-8c887b4e6c5e</b></p><a name=\"9583c018-8e84-4729-9ac0-8c887b4e6c5e\"> </a><a name=\"hc9583c018-8e84-4729-9ac0-8c887b4e6c5e\"> </a><div style=\"display: inline-block; background-color: #d9e0e7; padding: 6px; margin: 4px; border: 1px solid #8da1b4; border-radius: 5px; line-height: 60%\"><p style=\"margin-bottom: 0px\"/><p style=\"margin-bottom: 0px\">Profile: <a href=\"http://medcomfhir.dk/ig/core/3.0.1/StructureDefinition-medcom-core-practitioner.html\">MedComCorePractitionerversion: null3.0.1)</a></p></div><p><b>name</b>: Michael Burns </p></div>"
  },
  "name" : [{
    "family" : "Burns",
    "given" : ["Michael"]
  }]
}