<?xml version="1.0" encoding="UTF-8"?><Bundle xmlns="http://hl7.org/fhir"><type value="collection"/><entry><resource><OperationOutcome><issue><extension url="http://hl7.org/fhir/StructureDefinition/operationoutcome-issue-source"><valueString value="Publisher"/></extension><severity value="warning"/><code value="not-found"/><details><text value="The HTML fragment 'ip-statements.xhtml' is not included anywhere in the produced implementation guide"/></details><expression value="1"/></issue><issue><extension url="http://hl7.org/fhir/StructureDefinition/operationoutcome-issue-source"><valueString value="Publisher"/></extension><severity value="warning"/><code value="not-found"/><details><text value="An HTML fragment from the set [cross-version-analysis.xhtml, cross-version-analysis-inline.xhtml] is not included anywhere in the produced implementation guide"/></details><expression value="2"/></issue><issue><extension url="http://hl7.org/fhir/StructureDefinition/operationoutcome-issue-source"><valueString value="Publisher"/></extension><severity value="warning"/><code value="not-found"/><details><text value="An HTML fragment from the set [dependency-table.xhtml, dependency-table-short.xhtml, dependency-table-nontech.xhtml] is not included anywhere in the produced implementation guide"/></details><expression value="3"/></issue><issue><extension url="http://hl7.org/fhir/StructureDefinition/operationoutcome-issue-source"><valueString value="Publisher"/></extension><severity value="warning"/><code value="not-found"/><details><text value="The HTML fragment 'globals-table.xhtml' is not included anywhere in the produced implementation guide"/></details><expression value="4"/></issue></OperationOutcome></resource></entry><entry><resource><OperationOutcome><extension url="http://hl7.org/fhir/StructureDefinition/operationoutcome-file"><valueString value="/tmp/ig-builds/medcom.fhir.dk.xdsmetadata#1.0.1-milestone/fsh-generated/resources/CodeSystem-MedCom-ihe-classcode-CS"/></extension></OperationOutcome></resource></entry><entry><resource><OperationOutcome><extension url="http://hl7.org/fhir/StructureDefinition/operationoutcome-file"><valueString value="/tmp/ig-builds/medcom.fhir.dk.xdsmetadata#1.0.1-milestone/fsh-generated/resources/CodeSystem-MedCom-ihe-formatcode-CS"/></extension></OperationOutcome></resource></entry><entry><resource><OperationOutcome><extension url="http://hl7.org/fhir/StructureDefinition/operationoutcome-file"><valueString value="/tmp/ig-builds/medcom.fhir.dk.xdsmetadata#1.0.1-milestone/fsh-generated/resources/CodeSystem-MedCom-ihe-homeCommunityId-CS"/></extension></OperationOutcome></resource></entry><entry><resource><OperationOutcome><extension url="http://hl7.org/fhir/StructureDefinition/operationoutcome-file"><valueString value="/tmp/ig-builds/medcom.fhir.dk.xdsmetadata#1.0.1-milestone/fsh-generated/resources/CodeSystem-MedCom-ihe-typecode-CS"/></extension></OperationOutcome></resource></entry><entry><resource><OperationOutcome><extension url="http://hl7.org/fhir/StructureDefinition/operationoutcome-file"><valueString value="/tmp/ig-builds/medcom.fhir.dk.xdsmetadata#1.0.1-milestone/fsh-generated/resources/ImplementationGuide-medcom.fhir.dk.xdsmetadata"/></extension></OperationOutcome></resource></entry><entry><resource><OperationOutcome><extension url="http://hl7.org/fhir/StructureDefinition/operationoutcome-file"><valueString value="/tmp/ig-builds/medcom.fhir.dk.xdsmetadata#1.0.1-milestone/fsh-generated/resources/ValueSet-MedCom-dk-ihe-plr-typecode-VS"/></extension><issue><extension url="http://hl7.org/fhir/StructureDefinition/operationoutcome-issue-line"><valueInteger value="1"/></extension><extension url="http://hl7.org/fhir/StructureDefinition/operationoutcome-issue-col"><valueInteger value="1274"/></extension><extension url="http://hl7.org/fhir/StructureDefinition/operationoutcome-issue-source"><valueString value="InstanceValidator"/></extension><extension url="http://hl7.org/fhir/StructureDefinition/operationoutcome-message-id"><valueCode value="VALUESET_INCLUDE_WRONG_CS_OID"/></extension><severity value="error"/><code value="invalid"/><details><text value="It is not valid to refer to a CodeSystem by an identifier like this 'urn:oid:2.16.840.1.113883.6.1'"/></details><expression value="ValueSet/MedCom-dk-ihe-plr-typecode-VS: ValueSet.compose.include[0]"/></issue><issue><extension url="http://hl7.org/fhir/StructureDefinition/operationoutcome-issue-source"><valueString value="InstanceValidator"/></extension><extension url="http://hl7.org/fhir/StructureDefinition/operationoutcome-message-id"><valueCode value="VALUESET_UNC_SYSTEM_WARNING"/></extension><severity value="warning"/><code value="business-rule"/><details><text value="Unknown System 'urn:oid:2.16.840.1.113883.6.1' specified, so Concepts and Filters can't be checked (Details: A definition for CodeSystem 'urn:oid:2.16.840.1.113883.6.1' could not be found, so the code cannot be validated)"/></details><expression value="ValueSet/MedCom-dk-ihe-plr-typecode-VS: ValueSet.compose.include[0]"/></issue><issue><extension url="http://hl7.org/fhir/StructureDefinition/operationoutcome-issue-source"><valueString value="TerminologyEngine"/></extension><severity value="warning"/><code value="exception"/><details><text value="Error from http://tx.fhir.org/r4: Unable to provide support for code system urn:oid:2.16.840.1.113883.6.1"/></details><expression value="ValueSet.where(id = 'MedCom-dk-ihe-plr-typecode-VS')"/></issue></OperationOutcome></resource></entry><entry><resource><OperationOutcome><extension url="http://hl7.org/fhir/StructureDefinition/operationoutcome-file"><valueString value="/tmp/ig-builds/medcom.fhir.dk.xdsmetadata#1.0.1-milestone/fsh-generated/resources/ValueSet-MedCom-ihe-core-HealthcareFacilityTypeCode-VS"/></extension><issue><extension url="http://hl7.org/fhir/StructureDefinition/operationoutcome-issue-line"><valueInteger value="1"/></extension><extension url="http://hl7.org/fhir/StructureDefinition/operationoutcome-issue-col"><valueInteger value="8700"/></extension><extension url="http://hl7.org/fhir/StructureDefinition/operationoutcome-issue-source"><valueString value="InstanceValidator"/></extension><extension url="http://hl7.org/fhir/StructureDefinition/operationoutcome-message-id"><valueCode value="VALUESET_INCLUDE_WRONG_CS_OID"/></extension><severity value="error"/><code value="invalid"/><details><text value="It is not valid to refer to a CodeSystem by an identifier like this 'urn:oid:2.16.840.1.113883.6.96'"/></details><expression value="ValueSet/MedCom-ihe-core-HealthcareFacilityTypeCode-VS: ValueSet.compose.include[0]"/></issue><issue><extension url="http://hl7.org/fhir/StructureDefinition/operationoutcome-issue-source"><valueString value="InstanceValidator"/></extension><extension url="http://hl7.org/fhir/StructureDefinition/operationoutcome-message-id"><valueCode value="VALUESET_UNC_SYSTEM_WARNING"/></extension><severity value="warning"/><code value="business-rule"/><details><text value="Unknown System 'urn:oid:2.16.840.1.113883.6.96' specified, so Concepts and Filters can't be checked (Details: A definition for CodeSystem 'urn:oid:2.16.840.1.113883.6.96' could not be found, so the code cannot be validated)"/></details><expression value="ValueSet/MedCom-ihe-core-HealthcareFacilityTypeCode-VS: ValueSet.compose.include[0]"/></issue><issue><extension url="http://hl7.org/fhir/StructureDefinition/operationoutcome-issue-source"><valueString value="TerminologyEngine"/></extension><severity value="warning"/><code value="exception"/><details><text value="Error from http://tx.fhir.org/r4: Unable to provide support for code system urn:oid:2.16.840.1.113883.6.96"/></details><expression value="ValueSet.where(id = 'MedCom-ihe-core-HealthcareFacilityTypeCode-VS')"/></issue></OperationOutcome></resource></entry><entry><resource><OperationOutcome><extension url="http://hl7.org/fhir/StructureDefinition/operationoutcome-file"><valueString value="/tmp/ig-builds/medcom.fhir.dk.xdsmetadata#1.0.1-milestone/fsh-generated/resources/ValueSet-MedCom-ihe-core-PracticeSettingCode-VS"/></extension><issue><extension url="http://hl7.org/fhir/StructureDefinition/operationoutcome-issue-line"><valueInteger value="1"/></extension><extension url="http://hl7.org/fhir/StructureDefinition/operationoutcome-issue-col"><valueInteger value="7304"/></extension><extension url="http://hl7.org/fhir/StructureDefinition/operationoutcome-issue-source"><valueString value="InstanceValidator"/></extension><extension url="http://hl7.org/fhir/StructureDefinition/operationoutcome-message-id"><valueCode value="VALUESET_INCLUDE_WRONG_CS_OID"/></extension><severity value="error"/><code value="invalid"/><details><text value="It is not valid to refer to a CodeSystem by an identifier like this 'urn:oid:2.16.840.1.113883.6.96'"/></details><expression value="ValueSet/MedCom-ihe-core-PracticeSettingCode-VS: ValueSet.compose.include[0]"/></issue><issue><extension url="http://hl7.org/fhir/StructureDefinition/operationoutcome-issue-source"><valueString value="InstanceValidator"/></extension><extension url="http://hl7.org/fhir/StructureDefinition/operationoutcome-message-id"><valueCode value="VALUESET_UNC_SYSTEM_WARNING"/></extension><severity value="warning"/><code value="business-rule"/><details><text value="Unknown System 'urn:oid:2.16.840.1.113883.6.96' specified, so Concepts and Filters can't be checked (Details: A definition for CodeSystem 'urn:oid:2.16.840.1.113883.6.96' could not be found, so the code cannot be validated)"/></details><expression value="ValueSet/MedCom-ihe-core-PracticeSettingCode-VS: ValueSet.compose.include[0]"/></issue><issue><extension url="http://hl7.org/fhir/StructureDefinition/operationoutcome-issue-source"><valueString value="TerminologyEngine"/></extension><severity value="warning"/><code value="exception"/><details><text value="Error from http://tx.fhir.org/r4: Unable to provide support for code system urn:oid:2.16.840.1.113883.6.96"/></details><expression value="ValueSet.where(id = 'MedCom-ihe-core-PracticeSettingCode-VS')"/></issue></OperationOutcome></resource></entry><entry><resource><OperationOutcome><extension url="http://hl7.org/fhir/StructureDefinition/operationoutcome-file"><valueString value="/tmp/ig-builds/medcom.fhir.dk.xdsmetadata#1.0.1-milestone/fsh-generated/resources/ValueSet-MedCom-ihe-core-classcode-VS"/></extension><issue><extension url="http://hl7.org/fhir/StructureDefinition/operationoutcome-issue-line"><valueInteger value="1"/></extension><extension url="http://hl7.org/fhir/StructureDefinition/operationoutcome-issue-col"><valueInteger value="1123"/></extension><extension url="http://hl7.org/fhir/StructureDefinition/operationoutcome-issue-source"><valueString value="InstanceValidator"/></extension><extension url="http://hl7.org/fhir/StructureDefinition/operationoutcome-message-id"><valueCode value="Type_Specific_Checks_DT_URL_Resolve"/></extension><severity value="warning"/><code value="invalid"/><details><text value="URL value 'urn:oid:1.2.208.184.100.9' does not resolve"/></details><expression value="ValueSet/MedCom-ihe-core-classcode-VS: ValueSet.compose.include[0].system"/></issue><issue><extension url="http://hl7.org/fhir/StructureDefinition/operationoutcome-issue-source"><valueString value="InstanceValidator"/></extension><extension url="http://hl7.org/fhir/StructureDefinition/operationoutcome-message-id"><valueCode value="VALUESET_UNC_SYSTEM_WARNING"/></extension><severity value="warning"/><code value="business-rule"/><details><text value="Unknown System 'urn:oid:1.2.208.184.100.9' specified, so Concepts and Filters can't be checked (Details: A definition for CodeSystem 'urn:oid:1.2.208.184.100.9' could not be found, so the code cannot be validated)"/></details><expression value="ValueSet/MedCom-ihe-core-classcode-VS: ValueSet.compose.include[0]"/></issue><issue><extension url="http://hl7.org/fhir/StructureDefinition/operationoutcome-issue-source"><valueString value="TerminologyEngine"/></extension><severity value="warning"/><code value="exception"/><details><text value="Error from http://tx.fhir.org/r4: Unable to provide support for code system urn:oid:1.2.208.184.100.9"/></details><expression value="ValueSet.where(id = 'MedCom-ihe-core-classcode-VS')"/></issue></OperationOutcome></resource></entry><entry><resource><OperationOutcome><extension url="http://hl7.org/fhir/StructureDefinition/operationoutcome-file"><valueString value="/tmp/ig-builds/medcom.fhir.dk.xdsmetadata#1.0.1-milestone/fsh-generated/resources/ValueSet-MedCom-ihe-core-confidentialitycode-VS"/></extension><issue><extension url="http://hl7.org/fhir/StructureDefinition/operationoutcome-issue-line"><valueInteger value="1"/></extension><extension url="http://hl7.org/fhir/StructureDefinition/operationoutcome-issue-col"><valueInteger value="1216"/></extension><extension url="http://hl7.org/fhir/StructureDefinition/operationoutcome-issue-source"><valueString value="InstanceValidator"/></extension><extension url="http://hl7.org/fhir/StructureDefinition/operationoutcome-message-id"><valueCode value="VALUESET_INCLUDE_WRONG_CS_OID"/></extension><severity value="error"/><code value="invalid"/><details><text value="It is not valid to refer to a CodeSystem by an identifier like this 'urn:oid:2.16.840.1.113883.5.25'"/></details><expression value="ValueSet/MedCom-ihe-core-confidentialitycode-VS: ValueSet.compose.include[0]"/></issue><issue><extension url="http://hl7.org/fhir/StructureDefinition/operationoutcome-issue-source"><valueString value="InstanceValidator"/></extension><extension url="http://hl7.org/fhir/StructureDefinition/operationoutcome-message-id"><valueCode value="VALUESET_UNC_SYSTEM_WARNING"/></extension><severity value="warning"/><code value="business-rule"/><details><text value="Unknown System 'urn:oid:2.16.840.1.113883.5.25' specified, so Concepts and Filters can't be checked (Details: A definition for CodeSystem 'urn:oid:2.16.840.1.113883.5.25' could not be found, so the code cannot be validated)"/></details><expression value="ValueSet/MedCom-ihe-core-confidentialitycode-VS: ValueSet.compose.include[0]"/></issue><issue><extension url="http://hl7.org/fhir/StructureDefinition/operationoutcome-issue-source"><valueString value="TerminologyEngine"/></extension><severity value="warning"/><code value="exception"/><details><text value="Error from http://tx.fhir.org/r4: Unable to provide support for code system urn:oid:2.16.840.1.113883.5.25"/></details><expression value="ValueSet.where(id = 'MedCom-ihe-core-confidentialitycode-VS')"/></issue></OperationOutcome></resource></entry><entry><resource><OperationOutcome><extension url="http://hl7.org/fhir/StructureDefinition/operationoutcome-file"><valueString value="/tmp/ig-builds/medcom.fhir.dk.xdsmetadata#1.0.1-milestone/fsh-generated/resources/ValueSet-MedCom-ihe-core-eventcodelist-VS"/></extension><issue><extension url="http://hl7.org/fhir/StructureDefinition/operationoutcome-issue-line"><valueInteger value="1"/></extension><extension url="http://hl7.org/fhir/StructureDefinition/operationoutcome-issue-col"><valueInteger value="3628"/></extension><extension url="http://hl7.org/fhir/StructureDefinition/operationoutcome-issue-source"><valueString value="InstanceValidator"/></extension><extension url="http://hl7.org/fhir/StructureDefinition/operationoutcome-message-id"><valueCode value="Type_Specific_Checks_DT_URL_Resolve"/></extension><severity value="warning"/><code value="invalid"/><details><text value="URL value 'urn:oid:1.2.208.176.2.4' does not resolve"/></details><expression value="ValueSet/MedCom-ihe-core-eventcodelist-VS: ValueSet.compose.include[0].system"/></issue><issue><extension url="http://hl7.org/fhir/StructureDefinition/operationoutcome-issue-line"><valueInteger value="1"/></extension><extension url="http://hl7.org/fhir/StructureDefinition/operationoutcome-issue-col"><valueInteger value="4100"/></extension><extension url="http://hl7.org/fhir/StructureDefinition/operationoutcome-issue-source"><valueString value="InstanceValidator"/></extension><extension url="http://hl7.org/fhir/StructureDefinition/operationoutcome-message-id"><valueCode value="Type_Specific_Checks_DT_URL_Resolve"/></extension><severity value="warning"/><code value="invalid"/><details><text value="URL value 'urn:oid:1.2.208.176.7.3.1' does not resolve"/></details><expression value="ValueSet/MedCom-ihe-core-eventcodelist-VS: ValueSet.compose.include[1].system"/></issue><issue><extension url="http://hl7.org/fhir/StructureDefinition/operationoutcome-issue-line"><valueInteger value="1"/></extension><extension url="http://hl7.org/fhir/StructureDefinition/operationoutcome-issue-col"><valueInteger value="4492"/></extension><extension url="http://hl7.org/fhir/StructureDefinition/operationoutcome-issue-source"><valueString value="InstanceValidator"/></extension><extension url="http://hl7.org/fhir/StructureDefinition/operationoutcome-message-id"><valueCode value="Type_Specific_Checks_DT_URL_Resolve"/></extension><severity value="warning"/><code value="invalid"/><details><text value="URL value 'urn:oid:1.2.208.176.2.1' does not resolve"/></details><expression value="ValueSet/MedCom-ihe-core-eventcodelist-VS: ValueSet.compose.include[2].system"/></issue><issue><extension url="http://hl7.org/fhir/StructureDefinition/operationoutcome-issue-line"><valueInteger value="1"/></extension><extension url="http://hl7.org/fhir/StructureDefinition/operationoutcome-issue-col"><valueInteger value="5012"/></extension><extension url="http://hl7.org/fhir/StructureDefinition/operationoutcome-issue-source"><valueString value="InstanceValidator"/></extension><extension url="http://hl7.org/fhir/StructureDefinition/operationoutcome-message-id"><valueCode value="Type_Specific_Checks_DT_URL_Resolve"/></extension><severity value="warning"/><code value="invalid"/><details><text value="URL value 'urn:oid:1.2.208.184.100.1' does not resolve"/></details><expression value="ValueSet/MedCom-ihe-core-eventcodelist-VS: ValueSet.compose.include[3].system"/></issue><issue><extension url="http://hl7.org/fhir/StructureDefinition/operationoutcome-issue-line"><valueInteger value="1"/></extension><extension url="http://hl7.org/fhir/StructureDefinition/operationoutcome-issue-col"><valueInteger value="5246"/></extension><extension url="http://hl7.org/fhir/StructureDefinition/operationoutcome-issue-source"><valueString value="InstanceValidator"/></extension><extension url="http://hl7.org/fhir/StructureDefinition/operationoutcome-message-id"><valueCode value="Type_Specific_Checks_DT_URL_Resolve"/></extension><severity value="warning"/><code value="invalid"/><details><text value="URL value 'urn:ad:dk:medcom:noah:action-categories' does not resolve"/></details><expression value="ValueSet/MedCom-ihe-core-eventcodelist-VS: ValueSet.compose.include[4].system"/></issue><issue><extension url="http://hl7.org/fhir/StructureDefinition/operationoutcome-issue-source"><valueString value="InstanceValidator"/></extension><extension url="http://hl7.org/fhir/StructureDefinition/operationoutcome-message-id"><valueCode value="VALUESET_UNC_SYSTEM_WARNING"/></extension><severity value="warning"/><code value="business-rule"/><details><text value="Unknown System 'urn:oid:1.2.208.176.2.4' specified, so Concepts and Filters can't be checked (Details: A definition for CodeSystem 'urn:oid:1.2.208.176.2.4' could not be found, so the code cannot be validated)"/></details><expression value="ValueSet/MedCom-ihe-core-eventcodelist-VS: ValueSet.compose.include[0]"/></issue><issue><extension url="http://hl7.org/fhir/StructureDefinition/operationoutcome-issue-source"><valueString value="InstanceValidator"/></extension><extension url="http://hl7.org/fhir/StructureDefinition/operationoutcome-message-id"><valueCode value="VALUESET_UNC_SYSTEM_WARNING"/></extension><severity value="warning"/><code value="business-rule"/><details><text value="Unknown System 'urn:oid:1.2.208.176.7.3.1' specified, so Concepts and Filters can't be checked (Details: A definition for CodeSystem 'urn:oid:1.2.208.176.7.3.1' could not be found, so the code cannot be validated)"/></details><expression value="ValueSet/MedCom-ihe-core-eventcodelist-VS: ValueSet.compose.include[1]"/></issue><issue><extension url="http://hl7.org/fhir/StructureDefinition/operationoutcome-issue-source"><valueString value="InstanceValidator"/></extension><extension url="http://hl7.org/fhir/StructureDefinition/operationoutcome-message-id"><valueCode value="VALUESET_UNC_SYSTEM_WARNING"/></extension><severity value="warning"/><code value="business-rule"/><details><text value="Unknown System 'urn:oid:1.2.208.176.2.1' specified, so Concepts and Filters can't be checked (Details: A definition for CodeSystem 'urn:oid:1.2.208.176.2.1' could not be found, so the code cannot be validated)"/></details><expression value="ValueSet/MedCom-ihe-core-eventcodelist-VS: ValueSet.compose.include[2]"/></issue><issue><extension url="http://hl7.org/fhir/StructureDefinition/operationoutcome-issue-source"><valueString value="InstanceValidator"/></extension><extension url="http://hl7.org/fhir/StructureDefinition/operationoutcome-message-id"><valueCode value="VALUESET_UNC_SYSTEM_WARNING"/></extension><severity value="warning"/><code value="business-rule"/><details><text value="Unknown System 'urn:oid:1.2.208.184.100.1' specified, so Concepts and Filters can't be checked (Details: A definition for CodeSystem 'urn:oid:1.2.208.184.100.1' could not be found, so the code cannot be validated)"/></details><expression value="ValueSet/MedCom-ihe-core-eventcodelist-VS: ValueSet.compose.include[3]"/></issue><issue><extension url="http://hl7.org/fhir/StructureDefinition/operationoutcome-issue-source"><valueString value="InstanceValidator"/></extension><extension url="http://hl7.org/fhir/StructureDefinition/operationoutcome-message-id"><valueCode value="VALUESET_UNC_SYSTEM_WARNING"/></extension><severity value="warning"/><code value="business-rule"/><details><text value="Unknown System 'urn:ad:dk:medcom:noah:action-categories' specified, so Concepts and Filters can't be checked (Details: A definition for CodeSystem 'urn:ad:dk:medcom:noah:action-categories' could not be found, so the code cannot be validated)"/></details><expression value="ValueSet/MedCom-ihe-core-eventcodelist-VS: ValueSet.compose.include[4]"/></issue><issue><extension url="http://hl7.org/fhir/StructureDefinition/operationoutcome-issue-source"><valueString value="TerminologyEngine"/></extension><severity value="warning"/><code value="exception"/><details><text value="Error from http://tx.fhir.org/r4: Unable to provide support for code system urn:oid:1.2.208.176.2.4"/></details><expression value="ValueSet.where(id = 'MedCom-ihe-core-eventcodelist-VS')"/></issue></OperationOutcome></resource></entry><entry><resource><OperationOutcome><extension url="http://hl7.org/fhir/StructureDefinition/operationoutcome-file"><valueString value="/tmp/ig-builds/medcom.fhir.dk.xdsmetadata#1.0.1-milestone/fsh-generated/resources/ValueSet-MedCom-ihe-core-formatcode-VS"/></extension></OperationOutcome></resource></entry><entry><resource><OperationOutcome><extension url="http://hl7.org/fhir/StructureDefinition/operationoutcome-file"><valueString value="/tmp/ig-builds/medcom.fhir.dk.xdsmetadata#1.0.1-milestone/fsh-generated/resources/ValueSet-MedCom-ihe-core-homeCommunityId-VS"/></extension><issue><extension url="http://hl7.org/fhir/StructureDefinition/operationoutcome-issue-line"><valueInteger value="1"/></extension><extension url="http://hl7.org/fhir/StructureDefinition/operationoutcome-issue-col"><valueInteger value="1343"/></extension><extension url="http://hl7.org/fhir/StructureDefinition/operationoutcome-issue-source"><valueString value="InstanceValidator"/></extension><extension url="http://hl7.org/fhir/StructureDefinition/operationoutcome-message-id"><valueCode value="Type_Specific_Checks_DT_URL_Resolve"/></extension><severity value="warning"/><code value="invalid"/><details><text value="URL value 'urn:oid:1.2.208.176.8.1' does not resolve"/></details><expression value="ValueSet/MedCom-ihe-core-homeCommunityId-VS: ValueSet.compose.include[0].system"/></issue><issue><extension url="http://hl7.org/fhir/StructureDefinition/operationoutcome-issue-source"><valueString value="InstanceValidator"/></extension><extension url="http://hl7.org/fhir/StructureDefinition/operationoutcome-message-id"><valueCode value="VALUESET_UNC_SYSTEM_WARNING"/></extension><severity value="warning"/><code value="business-rule"/><details><text value="Unknown System 'urn:oid:1.2.208.176.8.1' specified, so Concepts and Filters can't be checked (Details: A definition for CodeSystem 'urn:oid:1.2.208.176.8.1' could not be found, so the code cannot be validated)"/></details><expression value="ValueSet/MedCom-ihe-core-homeCommunityId-VS: ValueSet.compose.include[0]"/></issue><issue><extension url="http://hl7.org/fhir/StructureDefinition/operationoutcome-issue-line"><valueInteger value="1"/></extension><extension url="http://hl7.org/fhir/StructureDefinition/operationoutcome-issue-col"><valueInteger value="1587"/></extension><extension url="http://hl7.org/fhir/StructureDefinition/operationoutcome-issue-source"><valueString value="InstanceValidator"/></extension><severity value="warning"/><code value="required"/><details><text value="Published value sets SHOULD conform to the ShareableValueSet profile, which says that the element ValueSet.experimental is mandatory, but it is not present"/></details><expression value="ValueSet/MedCom-ihe-core-homeCommunityId-VS: ValueSet"/></issue><issue><extension url="http://hl7.org/fhir/StructureDefinition/operationoutcome-issue-source"><valueString value="TerminologyEngine"/></extension><severity value="warning"/><code value="exception"/><details><text value="Error from http://tx.fhir.org/r4: Unable to provide support for code system urn:oid:1.2.208.176.8.1"/></details><expression value="ValueSet.where(id = 'MedCom-ihe-core-homeCommunityId-VS')"/></issue></OperationOutcome></resource></entry><entry><resource><OperationOutcome><extension url="http://hl7.org/fhir/StructureDefinition/operationoutcome-file"><valueString value="/tmp/ig-builds/medcom.fhir.dk.xdsmetadata#1.0.1-milestone/fsh-generated/resources/ValueSet-MedCom-ihe-core-languagecode-VS"/></extension><issue><extension url="http://hl7.org/fhir/StructureDefinition/operationoutcome-issue-line"><valueInteger value="1"/></extension><extension url="http://hl7.org/fhir/StructureDefinition/operationoutcome-issue-col"><valueInteger value="1256"/></extension><extension url="http://hl7.org/fhir/StructureDefinition/operationoutcome-issue-source"><valueString value="InstanceValidator"/></extension><extension url="http://hl7.org/fhir/StructureDefinition/operationoutcome-message-id"><valueCode value="VALUESET_INCLUDE_WRONG_CS_OID"/></extension><severity value="error"/><code value="invalid"/><details><text value="It is not valid to refer to a CodeSystem by an identifier like this 'urn:oid:2.16.840.1.113883.6.121'"/></details><expression value="ValueSet/MedCom-ihe-core-languagecode-VS: ValueSet.compose.include[0]"/></issue><issue><extension url="http://hl7.org/fhir/StructureDefinition/operationoutcome-issue-source"><valueString value="InstanceValidator"/></extension><extension url="http://hl7.org/fhir/StructureDefinition/operationoutcome-message-id"><valueCode value="VALUESET_UNC_SYSTEM_WARNING"/></extension><severity value="warning"/><code value="business-rule"/><details><text value="Unknown System 'urn:oid:2.16.840.1.113883.6.121' specified, so Concepts and Filters can't be checked (Details: A definition for CodeSystem 'urn:oid:2.16.840.1.113883.6.121' could not be found, so the code cannot be validated)"/></details><expression value="ValueSet/MedCom-ihe-core-languagecode-VS: ValueSet.compose.include[0]"/></issue><issue><extension url="http://hl7.org/fhir/StructureDefinition/operationoutcome-issue-source"><valueString value="TerminologyEngine"/></extension><severity value="warning"/><code value="exception"/><details><text value="Error from http://tx.fhir.org/r4: Unable to provide support for code system urn:oid:2.16.840.1.113883.6.121"/></details><expression value="ValueSet.where(id = 'MedCom-ihe-core-languagecode-VS')"/></issue></OperationOutcome></resource></entry><entry><resource><OperationOutcome><extension url="http://hl7.org/fhir/StructureDefinition/operationoutcome-file"><valueString value="/tmp/ig-builds/medcom.fhir.dk.xdsmetadata#1.0.1-milestone/fsh-generated/resources/ValueSet-MedCom-ihe-core-mimetype-VS"/></extension><issue><extension url="http://hl7.org/fhir/StructureDefinition/operationoutcome-issue-line"><valueInteger value="1"/></extension><extension url="http://hl7.org/fhir/StructureDefinition/operationoutcome-issue-col"><valueInteger value="1470"/></extension><extension url="http://hl7.org/fhir/StructureDefinition/operationoutcome-issue-source"><valueString value="InstanceValidator"/></extension><extension url="http://hl7.org/fhir/StructureDefinition/operationoutcome-message-id"><valueCode value="VALUESET_INCLUDE_WRONG_CS_OID"/></extension><severity value="error"/><code value="invalid"/><details><text value="It is not valid to refer to a CodeSystem by an identifier like this 'urn:oid:2.16.840.1.113883.5.79'"/></details><expression value="ValueSet/MedCom-ihe-core-mimetype-VS: ValueSet.compose.include[0]"/></issue><issue><extension url="http://hl7.org/fhir/StructureDefinition/operationoutcome-issue-source"><valueString value="InstanceValidator"/></extension><extension url="http://hl7.org/fhir/StructureDefinition/operationoutcome-message-id"><valueCode value="VALUESET_UNC_SYSTEM_WARNING"/></extension><severity value="warning"/><code value="business-rule"/><details><text value="Unknown System 'urn:oid:2.16.840.1.113883.5.79' specified, so Concepts and Filters can't be checked (Details: A definition for CodeSystem 'urn:oid:2.16.840.1.113883.5.79' could not be found, so the code cannot be validated)"/></details><expression value="ValueSet/MedCom-ihe-core-mimetype-VS: ValueSet.compose.include[0]"/></issue><issue><extension url="http://hl7.org/fhir/StructureDefinition/operationoutcome-issue-source"><valueString value="TerminologyEngine"/></extension><severity value="warning"/><code value="exception"/><details><text value="Error from http://tx.fhir.org/r4: Unable to provide support for code system urn:oid:2.16.840.1.113883.5.79"/></details><expression value="ValueSet.where(id = 'MedCom-ihe-core-mimetype-VS')"/></issue></OperationOutcome></resource></entry><entry><resource><OperationOutcome><extension url="http://hl7.org/fhir/StructureDefinition/operationoutcome-file"><valueString value="/tmp/ig-builds/medcom.fhir.dk.xdsmetadata#1.0.1-milestone/fsh-generated/resources/ValueSet-MedCom-ihe-core-typecode-VS"/></extension><issue><extension url="http://hl7.org/fhir/StructureDefinition/operationoutcome-issue-line"><valueInteger value="1"/></extension><extension url="http://hl7.org/fhir/StructureDefinition/operationoutcome-issue-col"><valueInteger value="3309"/></extension><extension url="http://hl7.org/fhir/StructureDefinition/operationoutcome-issue-source"><valueString value="InstanceValidator"/></extension><extension url="http://hl7.org/fhir/StructureDefinition/operationoutcome-message-id"><valueCode value="Type_Specific_Checks_DT_URL_Resolve"/></extension><severity value="warning"/><code value="invalid"/><details><text value="URL value 'urn:oid:1.2.208.184.100.1' does not resolve"/></details><expression value="ValueSet/MedCom-ihe-core-typecode-VS: ValueSet.compose.include[1].system"/></issue><issue><extension url="http://hl7.org/fhir/StructureDefinition/operationoutcome-issue-line"><valueInteger value="1"/></extension><extension url="http://hl7.org/fhir/StructureDefinition/operationoutcome-issue-col"><valueInteger value="3271"/></extension><extension url="http://hl7.org/fhir/StructureDefinition/operationoutcome-issue-source"><valueString value="InstanceValidator"/></extension><extension url="http://hl7.org/fhir/StructureDefinition/operationoutcome-message-id"><valueCode value="VALUESET_INCLUDE_WRONG_CS_OID"/></extension><severity value="error"/><code value="invalid"/><details><text value="It is not valid to refer to a CodeSystem by an identifier like this 'urn:oid:2.16.840.1.113883.6.1'"/></details><expression value="ValueSet/MedCom-ihe-core-typecode-VS: ValueSet.compose.include[0]"/></issue><issue><extension url="http://hl7.org/fhir/StructureDefinition/operationoutcome-issue-source"><valueString value="InstanceValidator"/></extension><extension url="http://hl7.org/fhir/StructureDefinition/operationoutcome-message-id"><valueCode value="VALUESET_UNC_SYSTEM_WARNING"/></extension><severity value="warning"/><code value="business-rule"/><details><text value="Unknown System 'urn:oid:2.16.840.1.113883.6.1' specified, so Concepts and Filters can't be checked (Details: A definition for CodeSystem 'urn:oid:2.16.840.1.113883.6.1' could not be found, so the code cannot be validated)"/></details><expression value="ValueSet/MedCom-ihe-core-typecode-VS: ValueSet.compose.include[0]"/></issue><issue><extension url="http://hl7.org/fhir/StructureDefinition/operationoutcome-issue-source"><valueString value="InstanceValidator"/></extension><extension url="http://hl7.org/fhir/StructureDefinition/operationoutcome-message-id"><valueCode value="VALUESET_UNC_SYSTEM_WARNING"/></extension><severity value="warning"/><code value="business-rule"/><details><text value="Unknown System 'urn:oid:1.2.208.184.100.1' specified, so Concepts and Filters can't be checked (Details: A definition for CodeSystem 'urn:oid:1.2.208.184.100.1' could not be found, so the code cannot be validated)"/></details><expression value="ValueSet/MedCom-ihe-core-typecode-VS: ValueSet.compose.include[1]"/></issue><issue><extension url="http://hl7.org/fhir/StructureDefinition/operationoutcome-issue-source"><valueString value="TerminologyEngine"/></extension><severity value="warning"/><code value="exception"/><details><text value="Error from http://tx.fhir.org/r4: Unable to provide support for code system urn:oid:2.16.840.1.113883.6.1"/></details><expression value="ValueSet.where(id = 'MedCom-ihe-core-typecode-VS')"/></issue></OperationOutcome></resource></entry><entry><resource><OperationOutcome><extension url="http://hl7.org/fhir/StructureDefinition/operationoutcome-file"><valueString value="/tmp/ig-builds/medcom.fhir.dk.xdsmetadata#1.0.1-milestone/fsh-generated/resources/ValueSet-MedCom-ihe-plr-formatcode-VS"/></extension><issue><extension url="http://hl7.org/fhir/StructureDefinition/operationoutcome-issue-line"><valueInteger value="1"/></extension><extension url="http://hl7.org/fhir/StructureDefinition/operationoutcome-issue-col"><valueInteger value="1197"/></extension><extension url="http://hl7.org/fhir/StructureDefinition/operationoutcome-issue-source"><valueString value="InstanceValidator"/></extension><extension url="http://hl7.org/fhir/StructureDefinition/operationoutcome-message-id"><valueCode value="Type_Specific_Checks_DT_URL_Resolve"/></extension><severity value="warning"/><code value="invalid"/><details><text value="URL value 'urn:oid:1.2.208.184.100.10' does not resolve"/></details><expression value="ValueSet/MedCom-ihe-plr-formatcode-VS: ValueSet.compose.include[0].system"/></issue><issue><extension url="http://hl7.org/fhir/StructureDefinition/operationoutcome-issue-source"><valueString value="InstanceValidator"/></extension><extension url="http://hl7.org/fhir/StructureDefinition/operationoutcome-message-id"><valueCode value="VALUESET_UNC_SYSTEM_WARNING"/></extension><severity value="warning"/><code value="business-rule"/><details><text value="Unknown System 'urn:oid:1.2.208.184.100.10' specified, so Concepts and Filters can't be checked (Details: A definition for CodeSystem 'urn:oid:1.2.208.184.100.10' could not be found, so the code cannot be validated)"/></details><expression value="ValueSet/MedCom-ihe-plr-formatcode-VS: ValueSet.compose.include[0]"/></issue><issue><extension url="http://hl7.org/fhir/StructureDefinition/operationoutcome-issue-line"><valueInteger value="1"/></extension><extension url="http://hl7.org/fhir/StructureDefinition/operationoutcome-issue-col"><valueInteger value="1255"/></extension><extension url="http://hl7.org/fhir/StructureDefinition/operationoutcome-issue-source"><valueString value="InstanceValidator"/></extension><severity value="warning"/><code value="required"/><details><text value="Published value sets SHOULD conform to the ShareableValueSet profile, which says that the element ValueSet.experimental is mandatory, but it is not present"/></details><expression value="ValueSet/MedCom-ihe-plr-formatcode-VS: ValueSet"/></issue><issue><extension url="http://hl7.org/fhir/StructureDefinition/operationoutcome-issue-source"><valueString value="TerminologyEngine"/></extension><severity value="warning"/><code value="exception"/><details><text value="Error from http://tx.fhir.org/r4: Unable to provide support for code system urn:oid:1.2.208.184.100.10"/></details><expression value="ValueSet.where(id = 'MedCom-ihe-plr-formatcode-VS')"/></issue></OperationOutcome></resource></entry></Bundle>